{"cameraMode":{"drawMode":0,"name":"Shaded","section":"Shading Mode"},"sceneLighting":true,"audioPlay":false,"sceneViewState":{"m_AlwaysRefresh":false,"showFog":true,"showSkybox":true,"showFlares":true,"showImageEffects":true,"showParticleSystems":true,"showVisualEffectGraphs":true,"m_FxEnabled":true},"in2DMode":false,"pivot":{"x":-3.2450804710388185,"y":-7.608983993530273,"z":21.413862228393556},"rotation":{"x":-0.20288993418216706,"y":-0.0023514432832598688,"z":0.0004982899408787489,"w":-0.9792130589485169},"size":12.12435531616211,"orthographic":false}